gux/__init__.py
gux/__main__.py
gux/cli/__init__.py
gux/cli/dispatch.py
gux/cli/gux.py
gux/cli/main.py
gux-0.0.3.data/scripts/gux
gux-0.0.3.dist-info/LICENSE
gux-0.0.3.dist-info/METADATA
gux-0.0.3.dist-info/WHEEL
gux-0.0.3.dist-info/top_level.txt
gux-0.0.3.dist-info/RECORD
