Metadata-Version: 2.1
Name: gux
Version: 0.0.3
Summary: git user switcher
Home-page: https://github.com/azye/gux
Author: Alex Ye
Author-email: alexzye1@gmail.com
License: UNKNOWN
Platform: UNKNOWN
Requires-Python: >=3.6
